README.md
setup.py
execution_pipeline.egg-info/PKG-INFO
execution_pipeline.egg-info/SOURCES.txt
execution_pipeline.egg-info/dependency_links.txt
execution_pipeline.egg-info/requires.txt
execution_pipeline.egg-info/top_level.txt
pipeline/__init__.py
pipeline/helpers.py
pipeline/pipeline.py
pipeline/validators.py
pipeline/cache/__init__.py
pipeline/cache/memcache.py
pipeline/cache/mock.py
pipeline/cache/redis.py
pipeline/tests/__init__.py
pipeline/tests/test_helpers.py
pipeline/tests/test_pipeline_basics.py
pipeline/tests/test_pipeline_validation.py
pipeline/tests/test_special_cases.py
pipeline/tests/helpers/__init__.py
pipeline/tests/helpers/base_helpers.py