Metadata-Version: 2.1
Name: execution-pipeline
Version: 0.5.0
Summary: This library allows users to easily wrap functions with a series of decorators.
Home-page: https://bitbucket.org/jjorissen/python-pipeline
Author: John-Paul Jorissen
Author-email: jjorissen52@gmail.com
License: MIT
Keywords: python decorators execution pipeline execution_pipeline caching error handling
Platform: UNKNOWN
Classifier: Development Status :: 4 - Beta
Classifier: Intended Audience :: Developers
Classifier: Programming Language :: Python :: 3.6
Classifier: Programming Language :: Python :: 3.7
Classifier: Operating System :: Microsoft :: Windows :: Windows 10
Classifier: Operating System :: POSIX :: Linux
Classifier: Topic :: Office/Business
Classifier: License :: OSI Approved :: MIT License
Classifier: Programming Language :: Python :: 3.6
Requires-Python: >=3.6
Provides-Extra: memcache
Provides-Extra: redis
